libeasyobv/__init__.py
libeasyobv/easyobv.py
libeasyobv/fileops.py
libeasyobv-0.0.7.dist-info/LICENSE
libeasyobv-0.0.7.dist-info/METADATA
libeasyobv-0.0.7.dist-info/WHEEL
libeasyobv-0.0.7.dist-info/top_level.txt
libeasyobv-0.0.7.dist-info/RECORD
